api_calls/__init__.py
api_calls/docs_client.py
api_calls/drive_client.py
api_calls/gmail_client.py
api_calls/sheet_client.py
tests/__init__.py
tests/test_gmail_client.py
tests/test_sheet_client.py
api_services-0.1.1.dist-info/METADATA
api_services-0.1.1.dist-info/WHEEL
api_services-0.1.1.dist-info/top_level.txt
api_services-0.1.1.dist-info/RECORD
