Metadata-Version: 2.1
Name: api-services
Version: 0.1.1
Summary: A package for Google API services
Home-page: https://github.com/ayo-dev7/google_projects
Author: Damilola Adebiyi
Author-email: ayoadebiyi95@gmail.com
License: UNKNOWN
Platform: UNKNOWN
Classifier: Programming Language :: Python :: 3
Classifier: License :: OSI Approved :: MIT License
Classifier: Operating System :: OS Independent
Requires-Python: >=3.6
Requires-Dist: cachetools==5.5.0
Requires-Dist: google-api-python-client==2.146.0
Requires-Dist: google-auth==2.35.0
Requires-Dist: google-auth-oauthlib==1.2.1
Requires-Dist: httplib2==0.22.0
Requires-Dist: pandas==2.2.3
Requires-Dist: requests==2.32.3
Requires-Dist: requests-oauthlib==2.0.0
